Workbook

Sheet Overview
A1: Budget levels — 17 October 2026
A2: USD planning model; no hardware owned. Equipment estimates, professional time and human validation are separate. No purchase, flash, clinical approval or human-use authorization.
A4: Decision | B4: Recommended interpretation
A5: First bench | B5: A3: $12k–$25k equipment/setup; illustrative cart $17,203.20 including hardware reserve.
A6: Professionally run first phase | B6: Illustrative $77,920 before tax/freight, using one program reserve rather than double-counting the separate hardware reserve.
A7: Human-connected engineering | B7: Choose ONE cumulative B tier. B includes an approximately $20k baseline bench allowance; do not add the entire bench budget again.
A8: Physiological validation | B8: Choose ONE overall C program tier. Participant counts are planning scenarios, not powered designs. Custom device engineering is separate.
A9: Cash vs time | B9: Bench initial cash excludes labor. Unpaid owner hours have economic cost. The Labor and TCO sheet exposes professional-time assumptions.
A10: Recurring costs | B10: Bench annual allowances cover cash upkeep/access after year one, not recurring professional staff. Five-year cash = setup + four upkeep years.
A11: Price confidence | B11: Only named price anchors are observed listings. All wider budgets and rates are original planning assumptions, not supplier quotes.
A12: Source of truth | B12: Read the companion report for scope, exclusions, sources and safety gates. Current software remains nominal 50 kHz only.
A13: Safety | B13: Track A is passive-only. Neither an evaluation board nor the link-check ELF is cleared for human connection or flashing.
A14: Edit inputs | B14: Blue entries are editable assumptions. Excel/compatible software recalculates formulas on opening; initial formula caches are provided.

Sheet Assumptions
A1: Editable planning assumptions
A2: These are original scenario inputs, NOT wage surveys, facility quotes, powered study designs or guaranteed project costs.
A4: Input | B4: Value | C4: Unit / purpose
A5: Professional rate — low | B5: 150 | C5: USD/hour
A6: Professional rate — high | B6: 250 | C6: USD/hour
A7: Phase-1 rate | B7: 200 | C7: USD/hour
A8: Hardware reserve | B8: 0.2 | C8: fraction; cart only
A9: Program reserve | B9: 0.25 | C9: fraction; phase-1 or study scenario
A10: Participants in study example | B10: 300 | C10: illustrative; not powered
A11: Visits per participant | B11: 2 | C11: illustrative
A12: Cost per visit | B12: 800 | C12: USD; fully burdened assumption, define inclusions
A13: Study overhead | B13: 200000 | C13: USD beyond fully burdened visits; avoid duplicated costs
A14: Loaded FTE cost | B14: 240000 | C14: USD/person-year assumption
A15: FTE example headcount | B15: 4 | C15: people
A16: FTE example years | B16: 1 | C16: years
... A19: Independent DUT verification | B19: 8000 | C19: USD; distinct from initial standard/instrument calibration

Sheet Bench
A1: Track A — alternative passive-only setups
A2: Initial cash includes equipment/fixtures and specified initial services, excludes labor/tax/freight. Annual upkeep is modeled for years AFTER the initial year. Do not sum tiers.
A4: Tier | B4: Setup low | C4: Setup high | D4: Annual low | E4: Annual high | F4: Scope
A5: A1 Learning | B5: 1000 | C5: 3000 | D5: 200 | E5: 800 | F5: Bring-up, logging and simple passive checks; not traceable phase accuracy.
A6: A2 Shared reference | B6: 3000 | C6: 8000 | D6: 1000 | E6: 4000 | F6: Defined lab/rental/service campaign; rates and proper fixture require quotes.
A7: A3 Owned reference | B7: 12000 | C7: 25000 | D7: 1500 | E7: 4500 | F7: Appropriate LCR, correct fixture, calibration/standards, scope, DMM and DUT.
A8: A4 Premium characterization | B8: 35000 | C8: 100000 | D8: 3000 | E8: 10000 | F8: Advanced analyzer/workflow, programmable passive fixtures and temperature work.
A9: A5 Automated lab | B9: 100000 | C9: 300000 | D9: 8000 | E9: 30000 | F9: Automated regression/environment/unit-to-unit verification; upper bounds can be exceeded.

Sheet Labor and TCO
A1: Bench labor and five-year cash scenarios
A2: Professional work is one-time setup/characterization effort. Five-year cash excludes labor; professional staff for ongoing operations are NOT included. Tiers are alternatives.
A4: Tier | B4: Hours low | C4: Hours high | D4: Labor low | E4: Labor high | F4: Initial + labor low | G4: Initial + labor high | H4: Five-year cash low | I4: Five-year cash high
A5: A1 Learning | B5: 40 | C5: 120 | D5: =B5*Assumptions!$B$5 -> 6000 | E5: =C5*Assumptions!$B$6 -> 30000 | F5: =Bench!B5+D5 -> 7000 | G5: =Bench!C5+E5 -> 33000 | H5: =Bench!B5+(Assumptions!$B$17-1)*Bench!D5 -> 1800 | I5: =Bench!C5+(Assumptions!$B$17-1)*Bench!E5 -> 6200
A6: A2 Shared reference | B6: 80 | C6: 200 | D6: =B6*Assumptions!$B$5 -> 12000 | E6: =C6*Assumptions!$B$6 -> 50000 | F6: =Bench!B6+D6 -> 15000 | G6: =Bench!C6+E6 -> 58000 | H6: =Bench!B6+(Assumptions!$B$17-1)*Bench!D6 -> 7000 | I6: =Bench!C6+(Assumptions!$B$17-1)*Bench!E6 -> 24000
A7: A3 Owned reference | B7: 150 | C7: 400 | D7: =B7*Assumptions!$B$5 -> 22500 | E7: =C7*Assumptions!$B$6 -> 100000 | F7: =Bench!B7+D7 -> 34500 | G7: =Bench!C7+E7 -> 125000 | H7: =Bench!B7+(Assumptions!$B$17-1)*Bench!D7 -> 18000 | I7: =Bench!C7+(Assumptions!$B$17-1)*Bench!E7 -> 43000
A8: A4 Premium characterization | B8: 400 | C8: 1000 | D8: =B8*Assumptions!$B$5 -> 60000 | E8: =C8*Assumptions!$B$6 -> 250000 | F8: =Bench!B8+D8 -> 95000 | G8: =Bench!C8+E8 -> 350000 | H8: =Bench!B8+(Assumptions!$B$17-1)*Bench!D8 -> 47000 | I8: =Bench!C8+(Assumptions!$B$17-1)*Bench!E8 -> 140000
A9: A5 Automated lab | B9: 1500 | C9: 4000 | D9: =B9*Assumptions!$B$5 -> 225000 | E9: =C9*Assumptions!$B$6 -> 1000000 | F9: =Bench!B9+D9 -> 325000 | G9: =Bench!C9+E9 -> 1300000 | H9: =Bench!B9+(Assumptions!$B$17-1)*Bench!D9 -> 132000 | I9: =Bench!C9+(Assumptions!$B$17-1)*Bench!E9 -> 420000

Sheet Engineering
A1: Track B — cumulative custom-device engineering
A2: Includes an approximately $20k baseline bench allowance and engineering/compliance. Excludes large human studies, mass-production inventory and ongoing commercial operations. Choose ONE tier; do not sum.
A4: Tier | B4: Budget low | C4: Budget high | D4: Window | E4: Milestone / limits
A5: B1 Passive custom instrument | B5: 100000 | C5: 300000 | D5: 3–6 months | E5: Custom electronics, raw export, PCB iterations and passive verification; no human connection.
A6: B2 Reviewed research instrument | B6: 300000 | C6: 1000000 | D6: 6–12 months | E6: Complete safety architecture, specialist testing/documentation; human work requires appropriate approvals.
A7: B3 Segmental multifrequency platform | B7: 750000 | C7: 2500000 | D7: 12–24 months | E7: Characterized switching, contact QC, timing, mechanical/electrode/scale integration; not a validation result.
A8: B4 Productized composition platform | B8: 2000000 | C8: 8000000 | D8: 18–36+ months | E8: Manufacturing, quality, software lifecycle, usability/cybersecurity, regulatory program for chosen claims; can exceed range.

Sheet Validation
A1: Track C — physiological evidence programs
A2: Budgets through the stated milestone, including appropriate pilot/prep. Excludes custom device engineering and imaging-facility purchase. Counts are illustrative, not powered sample-size recommendations.
A4: Tier | B4: Budget low | C4: Budget high | D4: Participants low | E4: Participants high | F4: Scope
A5: C1 Repeatability/feasibility | B5: 50000 | C5: 200000 | D5: 20 | E5: 50 | F5: Repeated visits/comparators after approvals. Workflow and preliminary evidence, not universal accuracy.
A6: C2 Focused composition study | B6: 500000 | C6: 2000000 | D6: 300 | E6: 600 | F6: DXA/reference work, participant-level model holdout, specific population and claims.
A7: C3 Broader/multi-site validation | B7: 2000000 | C7: 8000000 | D7: 1000 | E7: 3000 | F7: Independent/subgroup/longitudinal evidence and selected MRI/4-compartment/fluid references; may exceed range.

Sheet Combined scenarios
A1: Combined program envelopes — not quotes
A2: Engineering B includes baseline bench allowance. Validation C excludes engineering. These rows are alternative scenarios; do NOT sum them, or add every earlier tier. Broader multi-modality scope can exceed all of these.
A4: Scenario | B4: Engineering choice | C4: Validation choice | D4: Combined low | E4: Combined high | F4: Interpretation
A5: Research feasibility | B5: B2 Reviewed research instrument | C5: C1 Repeatability/feasibility | D5: =Engineering!B6+Validation!B5 -> 350000 | E5: =Engineering!C6+Validation!C5 -> 1200000 | F5: No claim of certification, success, clearance or applicability to a person; major scope changes need re-estimation.
A6: Focused research platform | B6: B3 Segmental multifrequency platform | C6: C2 Focused composition study | D6: =Engineering!B7+Validation!B6 -> 1250000 | E6: =Engineering!C7+Validation!C6 -> 4500000 | F6: No claim of certification, success, clearance or applicability to a person; major scope changes need re-estimation.
A7: Product + broader validation | B7: B4 Productized composition platform | C7: C3 Broader/multi-site validation | D7: =Engineering!B8+Validation!B7 -> 4000000 | E7: =Engineering!C8+Validation!C7 -> 16000000 | F7: No claim of certification, success, clearance or applicability to a person; major scope changes need re-estimation.

Sheet A3 cart
A1: Illustrative A3 equipment/setup cart
A2: Only the $5,186 LCR line is a retrieved current listed-price anchor. Other entries are allowances; quotes, exact packing list, proper probe/fixture and uncertainty scope are required. Tax, freight, new computer and labor excluded.
A4: Item | B4: Quantity | C4: Unit allowance | D4: Extended | E4: Basis / qualification
A5: Kit / optional spare allowance | B5: 1 | C5: 1100 | D5: =B5*C5 -> 1100 | E5: Planning allowance, not a requirement to buy two kits. Confirm controller/Z-Test/cable contents.
A6: Hioki IM3536 | B6: 1 | C6: 5186 | D6: =B6*C6 -> 5186 | E6: Detailed TEquipment listing; probe/fixture separate; stock expected Oct 21, not verified on hand.
A7: Correct probe/interface/fixture | B7: 1 | C7: 1000 | D7: =B7*C7 -> 1000 | E7: Planning allowance; match the reference plane and passive DUT, not an arbitrary SMD accessory.
A8: Standards and initial AC calibration | B8: 1 | C8: 2000 | D8: =B8*C8 -> 2000 | E8: Planning allowance; frequency/phase/uncertainty scope must be applicable.
A9: DMM | B9: 1 | C9: 750 | D9: =B9*C9 -> 750 | E9: Planning allowance; not an AC phase reference.
A10: Oscilloscope | B10: 1 | C10: 1800 | D10: =B10*C10 -> 1800 | E10: Planning allowance; debug and timing, not a substitute for LCR reference.
A11: Bench supply | B11: 1 | C11: 500 | D11: =B11*C11 -> 500 | E11: Planning allowance; passive bench only.
A12: Additional passive fixture work | B12: 1 | C12: 1500 | D12: =B12*C12 -> 1500 | E12: Planning allowance distinct from the basic probe interface.
A13: ESD/cables/local logging | B13: 1 | C13: 500 | D13: =B13*C13 -> 500 | E13: Planning allowance; manufacturer-approved connection route only.
A14: Subtotal | D14: =SUM(D5:D13) -> 14336
A15: Hardware reserve | D15: =D14*Assumptions!$B$8 -> 2867.2
A16: Equipment allocation | D16: =D14+D15 -> 17203.2

Sheet Phase 1
A1: Professionally run first-phase example
A2: Uses cart SUBTOTAL without its separate reserve, then applies ONE program reserve. Engineering and independent verification are modeled allowances; no quotation or purchase authorization.
A4: Component | B4: Amount | C4: Meaning
A5: Equipment/setup before reserve | B5: ='A3 cart'!D14 -> 14336 | C5: Does not also include the cart’s 20% reserve.
A6: Professional work | B6: =Assumptions!$B$18*Assumptions!$B$7 -> 40000
A7: Independent DUT/fixture verification | B7: =Assumptions!$B$19 -> 8000 | C7: Different scope from initial reference/standards calibration; obtain an actual service proposal.
A8: Subtotal | B8: =SUM(B5:B7) -> 62336
A9: Program reserve | B9: =B8*Assumptions!$B$9 -> 15584
A10: Total | B10: =B8+B9 -> 77920
A12: Study example — not a protocol
A13: Fully burdened visit costs | B13: =Assumptions!$B$10*Assumptions!$B$11*Assumptions!$B$12 -> 480000
A14: Additional study overhead | B14: =Assumptions!$B$13 -> 200000
A15: Study example including reserve | B15: =(B13+B14)*(1+Assumptions!$B$9) -> 850000
A17: FTE example — not added to consultant hours
A18: Modeled team cost | B18: =Assumptions!$B$14*Assumptions!$B$15*Assumptions!$B$16 -> 960000

Sheet Ownership
A1: Ownership, subscriptions and evidence gates
A2: Price observations are not contracts. Recurring calibration/consumables can remain real costs in an entirely offline system. No legacy Withings account entitlements assumed.
A4: Check | B4: Required answer / evidence
A5: Offline operation | B5: Acquisition/local viewing after cancellation; installer/firmware access; required accounts and network documented.
A6: Raw data | B6: Sample per-path/per-frequency R/X/IQ export plus quality flags/config/calibration. CSV or a USB port alone is insufficient.
A7: License scope | B7: Perpetual vs annual/per-seat/per-test; API/export rights; used-unit transfer; cancellation behavior.
A8: Recurring costs | B8: Separate compulsory acquisition access from optional support, calibration, electrodes and financial leases.
A9: Hioki price anchor | B9: IM3536 $5,186 detailed TEquipment page; separate fixture/probe; expected Oct 21 stock, quote needed.
A10: AD5940 kit anchor | B10: Mouser detailed page: $497.15; possible 8% US tariff; distributor end-of-stock warning. Packing list must be confirmed.
A11: Keysight current family | B11: E4980BL US page: $7,391 / $10,839 / $14,264 for 300k/500k/1MHz configurations; options/fixture/quote required. E4980AL discontinued/currently supported.
A12: MFIA anchor | B12: Manufacturer displays $14,490 region-specific/ex-works. 500kHz base vs 5MHz upgrade/configuration must be quoted; not an all-options 5MHz price.
A13: Rental caution | B13: $649/month IM3536 appears in search only; detailed rental fetch did not substantiate rate. Do not book or budget it as confirmed.
A14: Safety boundary | B14: Evaluation board passive-only. Custom patient-connected work needs complete-system safety review and required approvals. Battery/USB isolation alone is not qualification.
A15: Validation boundary | B15: Models, appropriate comparators, independent participants/sites and honest errors are required; maximum frequency or displayed metric count does not establish validity.
